Workbook

Sheet Test Cases
A1: No. | B1: Code | C1: Group | D1: Test name | E1: What we are checking | F1: Priority | G1: Before you start | H1: Steps | I1: What should happen | J1: Can it be automated? | K1: Notes | L1: For the automation team | M1: Result | N1: Pass / Fail | O1: Tested by | P1: Date | Q1: Requires | R1: Supplier Rule | S1: Review
A2: 1 | B2: TC-SM-NAV-001 | C2: A. Getting to the seat map | D2: You can only pick seats on step 2 | E2: Seats can only be chosen after passenger details and a fare package are filled in. | F2: High | G2: See the 'Before every test' sheet. | H2: 1. Log in to Admin and go to Booking-Mid Office. 2. Pick the branch, agency and agent, search for a flight and press 'Book Flight'. 3. Look at the step names at the top before filling anything in. | I2: There are only TWO steps: '01 Passenger Info and Bundles' and '02 Ancillaries'. There is no third step. While step 2 has not been reached, there is no 'Select Seat' button to press. | J2: Yes | K2: The wizard used to have 3 steps. It changed to 2 steps on 15 Sep 2026. | Q2: Seat | S2: Approved
A3: 2 | B3: TC-SM-NAV-002 | C3: A. Getting to the seat map | D3: You cannot reach the seats without choosing a fare package | E3: A fare package must be chosen first, because it decides which seats you are allowed to take. | F3: High | G3: See the 'Before every test' sheet. | H3: 1. On step 1, fill in every box for every passenger. 2. Do NOT choose a fare package. 3. Press 'Next'. | I3: You are not allowed to move on. The message 'Bundle selection is required' appears. Step 2 is still not reached, so the seat map cannot be opened. | J3: Yes | Q3: Seat | S3: Approved
A4: 3 | B4: TC-SM-NAV-002b | C4: A. Getting to the seat map | D4: Missing passenger details and a missing fare package are both reported | E4: One kind of error must not hide the other. | F4: Medium | G4: See the 'Before every test' sheet. | H4: 1. On an empty step 1 (nothing filled in, no fare package), press 'Next'. 2. Now fill in every passenger box, still with no fare package, and press 'Next' again. | I4: First time: 'Required' appears under each empty passenger box. Second time: only 'Bundle selection is required' appears. Neither message hides the other, and step 2 is not reached either time. | J4: Yes | Q4: None | S4: Approved
A5: 4 | B5: TC-SM-NAV-003 | C5: A. Getting to the seat map | D5: 'Select Seat' opens the seat map | E5: The map that opens belongs to the flight whose button you pressed. | F5: High | G5: See the 'Before every test' sheet. | H5: 1. Reach step 2 with a fare package chosen. 2. Press 'Select Seat' for one passenger and one flight. | I5: The seat map opens full screen. Its title reads 'Seat Map - CAI -> JED - Onward' (the airports and direction of the flight you picked). You can see: the left panel, the seat chart, the colour key and the button at the bottom. | J5: Yes | L5: The map was rebuilt on 15 Sep 2026. It is now [role="dialog"] labelled by #seat-map-shell-title, with body.seat-map-shell-open. Old scripts looking for a PrimeNG p-dialog will fail. | Q5: Seat | S5: Approved
A6: 5 | B6: TC-SM-NAV-005 | C6: A. Getting to the seat map | D6: You can skip seats completely | E6: Seats are optional - the booking must still work with no seat chosen. | F6: High | G6: See the 'Before every test' sheet. | H6: 1. Open the seat map and choose nothing. 2. Look at the button at the bottom. 3. Press 'Continue without seats'. | I6: With no seat chosen the bottom button reads 'Continue without seats'. Pressing it closes the map, gives nobody a seat, leaves the price unchanged, and the booking can still be finished. | J6: Yes | Q6: Seat | S6: Approved
A7: 6 | B7: TC-SM-RND-001 | C7: B. How the map is drawn | D7: The seat total matches the seats you can see | E7: If the map draws fewer seats than it claims, seats that could be sold are hidden. | F7: High | G7: See the 'Before every test' sheet. | H7: 1. Open the seat map. 2. Read the seat total in the left panel (shown as 'SEATS 174', for example). 3. Count the seats actually drawn. | I7: The two numbers are the same. Check that they match - do NOT expect a particular number, because every aircraft is different. | J7: Yes | Q7: Seat | S7: Approved
A8: 7 | B8: TC-SM-RND-002 | C8: B. How the map is drawn | D8: Every seat has one clear state and one seat number | E8: A seat with no state, or two seats with the same number, would break the booking. | F8: High | G8: See the 'Before every test' sheet. | H8: 1. Sort every seat into one group: free / costs money / taken / not offered to this passenger / women-only / held by someone else in your booking. 2. List every row and seat drawn. 3. Check each seat's label against the row it sits in. | I8: Every seat belongs to exactly one group, and the groups added together equal the seat total in the left panel. No seat number appears twice, and no seat is missing a state. | J8: Yes | K8: The list of states changed on 15 Sep 2026. | L8: Classes: seat--free, seat--unavailable, seat--not-offered, seat--female, seat--selected-other. A seat that costs money has none of --free or --unavailable; read its price from aria-label. | Q8: Seat | S8: Approved
A9: 8 | B9: TC-SM-RND-003 | C9: B. How the map is drawn | D9: Every seat has a full description | E9: The description is the only reliable place to read a seat's price and state. | F9: High | G9: See the 'Before every test' sheet. | H9: 1. Read the description of every seat. | I9: Each description is filled in and contains: seat number, row number, which block it is in, which section, any special features, and at the end either 'Blocked' or 'available for <price>'. The seat number in the description matches the number printed on the seat. | J9: Yes | L9: Read from aria-label on each seat button. | Q9: Seat | S9: Approved
A10: 9 | B10: TC-SM-RND-005 | C10: B. How the map is drawn | D10: Cabin and section information agrees with the map | E10: A whole cabin must not go missing from the map. | F10: Medium | G10: See the 'Before every test' sheet. | H10: 1. Compare the cabins named in the colour key with the cabins the seats actually belong to. 2. Compare each seat's section name with the section it is drawn under. 3. If the aircraft has an upper level as well as a lower one, check both are drawn. | I10: Every cabin named in the colour key exists on the map, and every cabin on the map is named in the colour key. The section names agree too. On an aircraft with two cabins, both must be shown - not only Economy. On a two-level aircraft, both levels must be shown. | J10: Yes | Q10: Seat | S10: Approved
A11: 10 | B11: TC-SM-RND-006 | C11: B. How the map is drawn | D11: The flight shown on the map is the flight you chose | E11: This proves the map is not an old or leftover one from a previous search. | F11: High | G11: See the 'Before every test' sheet. | H11: 1. Write down the route, flight number, aircraft type and times from the flight you selected. 2. Compare them with the flight details in the left panel of the seat map. | I11: All the details match, including the aircraft type. | J11: Yes | Q11: Seat | S11: Approved
A12: 11 | B12: TC-SM-RND-007 | C12: B. How the map is drawn | D12: Two different flights give two different maps | E12: Catches a map that is fixed in the code or reused from an earlier flight - the worst possible fault here. | F12: High | G12: See the 'Before every test' sheet. You also need a second flight using a DIFFERENT aircraft type. | H12: 1. Go through to the seat map for flight A and write down the aircraft, seat total, rows and layout. 2. Do the same for flight B, which uses a different aircraft type. | I12: The two maps are different, and each one matches its own aircraft. Neither map is a copy of the other. | J12: Partly | K12: You need a second flight on a different aircraft type; which aircraft flies a route is decided by the airline, so this cannot always be arranged. | Q12: Seat | S12: Approved
A13: 12 | B13: TC-SM-RND-010 | C13: B. How the map is drawn | D13: Each flight in a trip gets its own map | E13: On a return trip the second flight may be a different aircraft with a different layout. | F13: High | G13: See the 'Before every test' sheet. | H13: 1. Search a return trip (or a multi-city trip). 2. Reach step 2. 3. Open the seat map for each flight. | I13: There is a separate map for each flight, each titled with its own route and direction (Onward, Return). Each map matches its own aircraft. | J13: Yes | Q13: Seat | S13: Approved
A14: 13 | B14: TC-SM-STA-002 | C14: C. Seat colours and labels | D14: A taken seat can be looked at but not booked | E14: The system refuses by greying out the button, not by showing an error. | F14: High | G14: See the 'Before every test' sheet. | H14: 1. Click any seat shown as taken. 2. Look at the box that opens and at its button. | I14: The box opens and says 'Blocked' and 'Seat 13A is blocked.' The button is there but greyed out and now reads 'Seat unavailable'. No error message pops up, the seats-chosen count does not change, and any seat you already chose stays chosen. | J14: Yes | Q14: Seat | S14: Approved
A15: 14 | B15: TC-SM-STA-004 | C15: C. Seat colours and labels | D15: Seat features use known wording | E15: If the airline sends a new kind of feature, we must notice it instead of ignoring it. | F15: Medium | G15: See the 'Before every test' sheet. | H15: 1. Collect the feature words shown on all seats. 2. Compare them with the known list. 3. Open a seat that has more than one feature. | I15: Every feature word is one of these: Window seat, Aisle seat, Leg space seat, Chargeable seat, Exit and emergency exit, Female designated seat. Check that nothing unknown appears. Do NOT expect a particular feature to be present - each flight sends its own. | J15: Yes | K15: 'Chargeable seat' was missing from the 15 Sep map but present again on 17 Sep - it depends on the flight, so its absence is not a fault. | Q15: Seat | S15: Approved
A16: 15 | B16: TC-SM-STA-005 | C16: C. Seat colours and labels | D16: Window and aisle labels match where the seat really is | E16: A wrongly labelled seat means a passenger is sold something different from what they picked. | F16: Medium | G16: See the 'Before every test' sheet. | H16: 1. For every seat marked 'Window seat', check it really is at the edge of its row. 2. For every seat marked 'Aisle seat', check it really is next to the walkway. 3. Check middle seats carry neither label. | I16: The labels match the real position, whatever the layout is (2-2, 3-3, 3-4-3 and so on). Do NOT assume seats A and F are always windows - that is only true on this one aircraft. | J16: Yes | Q16: Seat | S16: Approved
A17: 16 | B17: TC-SM-STA-006 | C17: C. Seat colours and labels | D17: Emergency exit seats are marked | E17: Every exit-seat rule depends on being able to find these seats first. | F17: Medium | G17: See the 'Before every test' sheet. | H17: 1. Find the seats marked 'Exit and emergency exit'. 2. Check they sit next to each other and what else they are marked with. | I17: Exit seats are next to each other in their row and usually also marked 'Leg space seat'. Whether they are free to book depends on the airline - do not expect them always to be available. Two kinds of passenger may never sit there: an adult who has an infant with them, and a child. (Tested in detail in group P.) | J17: Yes | Q17: Seat | S17: Approved
A18: 17 | B18: TC-SM-STA-007 | C18: C. Seat colours and labels | D18: Women-only seats are marked clearly | E18: These seats must be explained, not just silently blocked. | F18: High | G18: See the 'Before every test' sheet. | H18: 1. Find the seats marked as women-only. 2. Check their labels, their markings and the colour key. | I18: Being a women-only seat does NOT by itself mean the seat is unavailable. For a male passenger it shows as unavailable and reads 'Female designated seat, not offered for <first name>'. For a female passenger the same seat becomes available and reads 'available for <price>'. | J18: Partly | K18: Only works on a flight that actually has women-only seats - skip cleanly when it does not. | L18: Classes: seat--female (always), plus seat--unavailable and seat--not-offered only when the passenger is male. | Q18: Seat | R18: ladies-only-seats | S18: Approved
A19: 18 | B19: TC-SM-SEL-001 | C19: D. Choosing a seat | D19: One click only shows the seat - it does not book it | E19: Stops a seat being booked by accident with a single click. | F19: Critical | G19: See the 'Before every test' sheet. | H19: 1. Open the seat map (the count reads 0 of N). 2. Click one free seat. 3. Do nothing else. | I19: An information box opens for that seat. The count still reads 0 of N, the passenger card still shows no seat, and the bottom button still reads 'Continue without seats'. Nothing has been booked. | J19: Yes | Q19: Seat | S19: Approved
A20: 19 | B20: TC-SM-SEL-002 | C20: D. Choosing a seat | D20: A seat is only taken when you press the button in the box | E20: The agent must always see which seat and which passenger they are confirming. | F20: Critical | G20: See the 'Before every test' sheet. | H20: 1. Click a free seat. 2. Read the wording on the button. 3. Press it. | I20: The button reads 'Book 5A for Mohanad' - the real seat number and the passenger's real first name from step 1. After pressing: the count goes up by one, the passenger card shows the seat, its cabin and its price, and the seat changes colour to show it is taken by you. | J20: Yes | Q20: Seat | S20: Approved
A21: 20 | B21: TC-SM-SEL-003 | C21: D. Choosing a seat | D21: The seat information box is correct | E21: This box is what the agent reads before deciding. | F21: High | G21: See the 'Before every test' sheet. | H21: 1. Click a seat. 2. Compare every line in the box with the seat's own description and with the left panel. | I21: The box shows the right state, seat number, price, cabin, where the seat sits in its row, and where the row sits in its section ('Row 5 - 5th of 7 rows in Y-1'). Everything agrees with the seat's own description. | J21: Yes | Q21: Seat | S21: Approved
A22: 21 | B22: TC-SM-SEL-006 | C22: D. Choosing a seat | D22: The bottom button changes as seats are chosen | E22: It is how the agent knows whether anything is currently held. | F22: High | G22: See the 'Before every test' sheet. | H22: 1. Note the bottom button with nothing chosen. 2. Choose a seat. 3. Read the button again. | I22: The button changes in this order: 'Continue without seats' -> 'Confirm 1 of 2 seats' -> 'Confirm 2 seats'. A 'Clear all seats' button sits next to it. The total counts only passengers who can have a seat - infants are not counted. Passenger cards show ACTIVE / SELECT / SELECTED / ASSIGNED. | J22: Yes | K22: The old wording 'Confirm seat' no longer exists. | L22: Buttons: button.confirm-action and button.confirm-reset. | Q22: Seat | S22: Approved
A23: 22 | B23: TC-SM-SEL-007 | C23: D. Choosing a seat | D23: Moving a passenger to another seat frees the first seat | E23: Otherwise one passenger holds two seats and a seat is lost from sale. | F23: High | G23: See the 'Before every test' sheet. | H23: 1. Give a passenger seat X. 2. Click seat Y and book it for the same passenger. | I23: The passenger has only seat Y. Seat X goes back to free, and the count still shows one seat for that passenger, not two. | J23: Yes | Q23: Seat | S23: Approved
A24: 23 | B24: TC-SM-SEL-008 | C24: D. Choosing a seat | D24: 'Clear all seats' also removes the seat charge | E24: Money must not stay on the booking for a seat nobody has. | F24: Medium | G24: See the 'Before every test' sheet. | H24: 1. Choose a seat. 2. Press 'Clear all seats'. | I24: All seats are given up, the count goes back to 0 of N, the seats become free again, the bottom button goes back to 'Continue without seats', and any seat charge disappears from the price breakdown. | J24: Yes | Q24: Seat | S24: Approved
A25: 24 | B25: TC-SM-SEL-009 | C25: D. Choosing a seat | D25: Confirming saves the seat and closes the map | E25: This is the record the agent and the airline both rely on. | F25: Critical | G25: See the 'Before every test' sheet. | H25: 1. Choose a seat. 2. Press the bottom button ('Confirm 1 seat'). 3. Read the 'Selected seats' list on step 2. | I25: The map closes and step 2 shows 'Selected seats - 1 traveller' with a line per passenger (name / seat / price) and the right prices. The button that opened the map now reads 'Change Seats'. If the seat cost money, a 'Seat Selection' line is added to the price breakdown. The seat number in the list is exactly the seat you clicked. | J25: Yes | Q25: Seat | S25: Approved
A26: 25 | B26: TC-SM-SEL-010 | C26: D. Choosing a seat | D26: 'Change Seats' reopens the map with your choice still there | E26: Looking at your choice again must not lose it. | F26: High | G26: See the 'Before every test' sheet. | H26: 1. Confirm a seat. 2. Press 'Change Seats'. | I26: The map opens again, the seat is still chosen, the count still shows it, and the passenger card still shows it. | J26: Yes | Q26: Seat | S26: Approved
A27: 26 | B27: TC-SM-SEL-012 | C27: D. Choosing a seat | D27: A seat held by another passenger in your booking is marked | E27: Two passengers must never hold the same seat. | F27: High | G27: See the 'Before every test' sheet. You need at least 2 passengers who can have a seat. | H27: 1. Give seat X to passenger A. 2. Switch to passenger B and click seat X. | I27: Seat X is shown as held and names who has it: 'selected for <A's full name>'. Passenger B cannot take it. | J27: Yes | K27: The business said this seat shows simply as 'Blocked'. What we actually saw names the holder, which is better - check which is intended. | L27: Class: seat--selected-other. | Q27: Seat | S27: Approved
A28: 27 | B28: TC-SM-MPX-002 | C28: E. More than one passenger or flight | D28: The seat goes to the passenger who is selected | E28: Stops a seat being given to the wrong passenger. | F28: Critical | G28: See the 'Before every test' sheet. You need at least 2 passengers. | H28: 1. With several passengers, note which card is selected and book a seat. 2. Click a different passenger's card. 3. Book a second seat. | I28: The first seat goes to the passenger who was selected, and the button named that passenger. The others still have no seat. After switching, the second seat goes to the newly selected passenger, the first passenger keeps theirs, and the count reads 2 of N. | J28: Yes | Q28: Seat | S28: Approved
A29: 28 | B29: TC-SM-MPX-004 | C29: E. More than one passenger or flight | D29: Two passengers cannot have the same seat | E29: The airline would reject a booking with one seat given to two people. | F29: Critical | G29: See the 'Before every test' sheet. You need at least 2 passengers. | H29: 1. Give seat X to passenger 1. 2. Select passenger 2 and try to book seat X. | I29: Passenger 2 cannot take seat X. It is shown as held, and it names who has it: 'selected for <full name>'. One seat must never be held by two passengers. | J29: Yes | K29: The business answered 'Blocked' on 17 Sep, but what we saw on 15 Sep also names the holder. Treat the named version as correct and report a plain 'Blocked' with no name. | L29: Class: seat--selected-other. | Q29: Seat | S29: Approved
A30: 29 | B30: TC-SM-MPX-006 | C30: E. More than one passenger or flight | D30: Seats on one flight do not affect the other flight | E30: Each flight of a return trip is seated separately. | F30: High | G30: See the 'Before every test' sheet. You need a return trip. | H30: 1. On a return trip, choose seats for the outbound flight and confirm. 2. Open the map for the return flight. 3. Choose a seat on the return flight. | I30: The return map starts empty - it does not copy the outbound seats. Choosing a return seat does not disturb the outbound one, and the summary shows each flight separately. | J30: Yes | Q30: Seat | S30: Approved
A31: 30 | B31: TC-SM-MPX-007 | C31: E. More than one passenger or flight | D31: Some passengers can have seats and others none | E31: Seats are optional for each passenger. | F31: Medium | G31: See the 'Before every test' sheet. You need 2 passengers. | H31: 1. With 2 passengers, give a seat to one only. 2. Confirm. | I31: Confirming is allowed with 1 of 2 chosen. The summary lists the one seated passenger, and the booking can still be finished. | J31: Yes | Q31: Seat | S31: Approved
A32: 31 | B32: TC-SM-PRC-001 | C32: F. Prices | D32: A seat included in the fare package costs nothing | E32: The agency must not pay twice for something the package already covers. | F32: Critical | G32: See the 'Before every test' sheet. The fare package must be 'Plus' (it says 'Seat selection: All seats'). Under 'Value' this test would correctly fail, because those seats are paid. | H32: 1. Choose the 'Plus' package. 2. Write down the amount to pay. 3. Choose a seat and confirm. | I32: The left panel reads 'No seat charges - Free', the seat's price reads 'Free', and the amount to pay does not change. The summary line for the seat shows a price of zero. | J32: Yes | Q32: Bundle + Seat | S32: Approved
A33: 32 | B33: TC-SM-PRC-002 | C33: F. Prices | D33: A seat marked 'Chargeable seat' must always have a price | E33: A seat described as chargeable must never be shown as free, whatever fare package is chosen. | F33: High | G33: See the 'Before every test' sheet. You need a flight that actually shows the words 'Chargeable seat' - check this first, because not every flight sends them. | H33: 1. Choose the 'Plus' package (it says 'Seat selection: All seats') and find a seat marked 'Chargeable seat'. 2. Write down the words on the seat and its price. 3. On the SAME flight, change to the 'Value' package and look at a seat marked the same way. 4. Check the amount to pay before and after booking such a seat. | I33: A seat marked 'Chargeable seat' ALWAYS has a price, under every fare package. If it shows 'Free', that is a FAULT - report it. Known fault seen on 09 Sep 2026: under 'Plus', seat 5A read 'Chargeable seat' and 'available for Free', the amount to pay did not change, and the summary showed a price of zero. Under 'Value' the behaviour was correct: seat 6C read 'Chargeable seat' with a price of EGP 642. | J33: Yes | K33: CORRECTED 17 Sep 2026. The business first said a free chargeable seat was acceptable, then ruled that a chargeable seat must always be paid. This test now looks for a fault instead of accepting the behaviour. 27 Sep 2026 (run-006): reproduced on flynas KSA, XY584. Confirmed as a bug by the business. | M33: Under 'Plus', all 36 seats marked 'Chargeable seat' showed 'available for Free' (e.g. 5A); the total did not change. Under 'Value' they were priced correctly. | N33: Fail | O33: Claude (run-006), for Mohanad Dawood | P33: 27 Sep 2026 | Q33: Seat | S33: Approved
A34: 33 | B34: TC-SM-PRC-003 | C34: F. Prices | D34: A paid seat is added as its own line in the price | E34: The agency must be able to see exactly what the seat cost. | F34: Critical | G34: See the 'Before every test' sheet. Use the 'Value' package, which does not include seat choice. | H34: 1. Choose the 'Value' package. 2. Open the seat map. 3. Choose a seat that has a price and confirm it. | I34: A 'Seat Selection' line appears in the price breakdown, separate from the fare package line. The amount to pay goes up by exactly the price of the seats chosen. Check the sum is right - do not expect a fixed amount, prices change per flight. | J34: Yes | K34: Was impossible to test before 15 Sep 2026, because no paid seat had ever been seen. | Q34: Seat | S34: Approved
A35: 34 | B35: TC-SM-PRC-003b | C35: F. Prices | D35: One aircraft can have several seat prices at once | E35: A price belongs to a seat and its section, not to the whole flight. | F35: High | G35: See the 'Before every test' sheet. Use the 'Value' package. | H35: 1. Group the seats by the price shown on each one. 2. Compare the groups with the price written above each section and with the colour key. | I35: Several different prices can appear on one aircraft, and that is correct. The price written above a section matches the seats in it ('from EGP 642', 'Free - EGP 642', 'All seats free'). Free and paid seats can be mixed inside ONE section, so never say 'rows 5 to 10 cost X' - a price belongs to a seat, not a row. | J35: Yes | K35: Seen on 15 Sep: Free / 422.91 / 1,097.91. Seen on 17 Sep: section Y-1 'from EGP 642', section Y-2 'Free - EGP 642'. | Q35: Seat | S35: Approved
A36: 35 | B36: TC-SM-PRC-004 | C36: F. Prices | D36: The price breakdown adds up | E36: This is the amount the agency wallet is actually charged. | F36: High | G36: See the 'Before every test' sheet. | H36: 1. Write down the base fare, the extras and each line under it, the taxes, the total and the amount to pay. 2. Add them up. | I36: The extras total equals the fare package + meal + baggage + seat. The amount to pay equals the base fare plus that total. The 'Seat Selection' line only appears once a PAID seat is confirmed. Check the sums, not the exact amounts. | J36: Yes | K36: Checked on 15 Sep 2026: 1,800 + 1,295.82 = 3,095.82, total 10,413.82 EGP. | Q36: Seat | S36: Approved
A37: 36 | B37: TC-SM-BND-002 | C37: G. Fare packages | D37: Changing the fare package recalculates the seats | E37: A seat that stays free after downgrading the package is money lost. | F37: Critical | G37: See the 'Before every test' sheet. | H37: 1. Choose the 'Plus' package on step 1, open the seat map and confirm a free seat. 2. Go back to step 1 and change the package to 'Value'. 3. Return to step 2, open the map again and read the prices and the total. | I37: The seat must either be given a price or be released. It must NOT stay free. The total must agree with the new price. This is the most important test in the suite - a free seat surviving the downgrade is direct money lost. | J37: Partly | K37: 27 Sep 2026 (run-006): business confirms this is a feature, not a defect - bundle change clears ancillaries, it does not recalculate them. Not retried; the stuck-wizard observation from the earlier 16 attempts stands as a separate item. | M37: The case's own premise was wrong. Per business decision, changing the fare package is not meant to recalculate the seats - it clears the ancillaries (seats, meals, bags) so the agent re-selects them under the new bundle. This run's attempts to observe a downgrade never reached that point: after downgrading Plus -> Value, advancing to step 2 failed twice with a sold-out ssr-quote error and the wizard stayed on step 1 with no visible message - a separate, still-open observation (tied to V6-12), not a failure of this case. | N37: Pass | O37: Claude (run-006), for Mohanad Dawood | P37: 27 Sep 2026 | Q37: Bundle + Seat | S37: Approved
A38: 37 | B38: TC-SM-BND-003 | C38: G. Fare packages | D38: Each flight uses its own fare package | E38: On a trip with two flights, each one is priced on its own terms. | F38: Medium | G38: See the 'Before every test' sheet. You need a trip with more than one flight. | H38: 1. Choose a different package for each flight - one that includes seats, one that does not. 2. Open the seat map for each flight. | I38: Each flight's seats are priced by ITS OWN package, independently of the other flight. | J38: Yes | Q38: Bundle | S38: Approved
A39: 38 | B39: TC-SM-BND-004 | C39: G. Fare packages | D39: Fare package names are never blank or repeated | E39: The agent must be able to tell the packages apart and get the one they picked. | F39: Medium | G39: See the 'Before every test' sheet. | H39: 1. Look at the list of fare packages offered. 2. Choose each one in turn and open the seat map. | I39: The Economy fare offers four clearly different names: 'Plus', 'Light Super Flex', 'Value', 'Value Flex'. No name is blank and no name appears twice. Each one can be chosen and leads to a working seat map. If a blank or repeated name comes back, report it - this used to happen and was fixed. | J39: Yes | K39: This test used to record the fault. Since 15 Sep 2026 it guards against the fault returning. | Q39: Bundle | S39: Approved
A40: 39 | B40: TC-SM-BND-005 | C40: G. Fare packages | D40: What the package promises about seats is what you get | E40: Promising seats the package does not give is mis-selling. | F40: High | G40: See the 'Before every test' sheet. Note the 'Seat selection: ...' line of the package you choose. | H40: 1. Read the 'Seat selection: ...' line in the package details. 2. Open the seat map and check which seats you can actually choose. | I40: What the package says matches what the map gives. Seen so far: 'All seats' gave 161 of 174 seats, all free. 'Premium' gave 4 of 174, free. 'Standard' gave 156 of 174, with 96 free and 60 paid. Check that the wording and the map agree - never expect these exact counts. | J40: Yes | Q40: Bundle + Seat | S40: Approved
A41: 40 | B41: TC-SM-GEN-001 | C41: H. Women-only seats | D41: A women-only seat is refused to a male passenger | E41: This is the base case the whole rule is judged against. | F41: High | G41: See the 'Before every test' sheet. Set the title to 'Mr'. | H41: 1. Fill in step 1 with the title 'Mr' (this makes the gender Male). 2. Go to step 2 and open the seat map. 3. Click a women-only seat. | I41: The seat shows as unavailable and reads 'Female designated seat, not offered for <first name>'. The button in the box is greyed out - there is no error pop-up. | J41: Yes | Q41: Seat | R41: ladies-only-seats | S41: Approved
A42: 41 | B42: TC-SM-GEN-002 | C42: H. Women-only seats | D42: A women-only seat is offered to a female passenger | E42: Proves the seat is kept for women, rather than being blocked for everybody. | F42: Critical | G42: See the 'Before every test' sheet. Set the title to 'Ms' or 'Mrs'. | H42: 1. Do the same booking with the title 'Ms' or 'Mrs' (this makes the gender Female). 2. Open the seat map for the same flight. 3. Click the same women-only seat. | I42: The seat is now available and reads 'Female designated seat, available for <price>'. It can be booked. Important: run this on an Economy fare whose package actually offers that part of the aircraft. On a fare that does not offer it, the seat would be unavailable anyway and the test would prove nothing. | J42: Yes | K42: Confirmed on 15 Sep 2026. | Q42: Seat | R42: ladies-only-seats | S42: Approved
A43: 42 | B43: TC-SM-GEN-002b | C43: H. Women-only seats | D43: The hidden seat data matches what is shown on screen | E43: The page carries the answer for every passenger at once - screen and data must agree. | F43: High | G43: See the 'Before every test' sheet. You need a booking with both a male and a female passenger, on an Economy fare that offers the women-only part of the aircraft. | H43: 1. Read the hidden data attached to every seat. 2. Read the part that lists the state for each passenger. 3. Switch between passengers and compare with what you can see and click. | I43: For every passenger, the hidden data says the same thing as the screen. Example: a women-only seat says blocked for the male passenger and available for the female one. Any disagreement either way is a fault. | J43: Yes | K43: Fastest way to check every passenger at once, without switching between them. | L43: data-seat-id is base64. Decoded: <flightKey>#<seat>#<overallState>#<perPaxStates>#<attributes>#<cabin>, where perPaxStates is like 0:Blocked,1:AvailablePaid. | Q43: Seat | R43: ladies-only-seats | S43: Approved
A44: 43 | B44: TC-SM-GEN-003 | C44: H. Women-only seats | D44: Gender comes from the title and cannot be edited | E44: The title is the only thing that controls women-only seats. | F44: Medium | G44: See the 'Before every test' sheet. | H44: 1. On step 1 set the title to 'Mr' and look at the gender box. 2. Try to change the gender directly. 3. Change the title to 'Ms'. | I44: The gender box cannot be edited. It reads 'Male' for 'Mr' and changes to 'Female' when the title becomes 'Ms' or 'Mrs'. | J44: Yes | Q44: None | S44: Approved
A45: 44 | B45: TC-SM-GEN-004 | C45: H. Women-only seats | D45: Each passenger sees their own seats in a mixed group | E45: Catches a map worked out once for the whole flight instead of per passenger. | F45: High | G45: See the 'Before every test' sheet. You need 2 adults, one 'Mr' and one 'Ms'. | H45: 1. Search for 2 adults and set one title to 'Mr' and the other to 'Ms'. 2. Open the seat map. 3. Switch between the two passengers and look at the women-only seats each time. | I45: The same seat reads 'not offered' for the male passenger and 'available for <price>' for the female one, with nothing else changed. The map updates straight away when you switch passenger. | J45: Yes | K45: Confirmed on 15 Sep 2026. | Q45: Seat | R45: ladies-only-seats | S45: Approved
A46: 45 | B46: TC-SM-GEN-005 | C46: H. Women-only seats | D46: Female titles are 'Ms' and 'Mrs', for children as well as adults | E46: Women-only seats depend on the title, and the same titles are offered to every passenger. | F46: Medium | G46: See the 'Before every test' sheet. The booking must include a child and an adult. | H46: 1. Add a child passenger and open the title list. 2. Open the title list for an adult as well. 3. Set the child's title to 'Ms', then to 'Mrs', and look at the women-only seats each time. | I46: Both children and adults are offered the SAME three titles: 'Mr', 'Ms' and 'Mrs'. There is no 'Miss' or 'Master'. 'Ms' and 'Mrs' both make the passenger female, and both give access to women-only seats. This is intended - do not report the missing child titles as a fault. | J46: Yes | K46: CORRECTED 17 Sep 2026: it is 'Ms' OR 'Mrs', and the title list is the same for children and adults. | Q46: Seat | R46: ladies-only-seats | S46: Approved
A47: 46 | B47: TC-SM-PER-001 | C47: I. Keeping the choice | D47: Seats survive going back a step | E47: Checking something on an earlier step must not throw the seats away. | F47: High | G47: See the 'Before every test' sheet. | H47: 1. Confirm a seat on step 2. 2. Press 'Prev' to step 1 and come back to step 2. 3. Read the seat and the total again. | I47: The 'Selected seats' list and the 'Change Seats' button are still there, the seat is still held, and the price is the same. | J47: Yes | Q47: Seat | S47: Approved
A48: 47 | B48: TC-SM-PER-002 | C48: I. Keeping the choice | D48: Seats, meals and bags all work together | E48: Choosing one extra must not wipe out another. | F48: High | G48: See the 'Before every test' sheet. | H48: 1. Choose a meal and an extra bag. 2. Choose and confirm a seat. 3. Look at the price breakdown. | I48: All three are kept at once and each has its own line in the price. Changing the meal or bag AFTER the seat is chosen must not lose the seat or change its price. | J48: Yes | Q48: Seat + Meal + Baggage | S48: Approved
A49: 48 | B49: TC-SM-PER-004 | C49: I. Keeping the choice | D49: What happens when the time limit runs out | E49: The booking offer is only held for a limited time. | F49: High | G49: See the 'Before every test' sheet. | H49: 1. Reach step 2 and note the 'Time left' countdown. 2. Let the time run out. 3. Try to open the seat map or choose a seat. | I49: The agent is sent back to the flight search page. It must not fail silently or pretend to work. Note whether any warning is shown first and whether the choices are lost. Do NOT write 60 minutes into the test: the time limit is 60 minutes for testing only and becomes 15 minutes when the system goes live. | J49: Partly | K49: Re-run this against the 15-minute limit before go-live. Waiting for real expiry is slow, so run it as a separate scheduled check. | Q49: None | S49: Approved
A50: 49 | B50: TC-SM-PER-007 | C50: I. Keeping the choice | D50: The seat appears on the payment summary | E50: What the agent sees before paying must be what gets booked. | F50: High | G50: See the 'Before every test' sheet. | H50: 1. Confirm a seat. 2. Look at the payment summary and price breakdown. DO NOT press 'Book'. | I50: The amount to pay and the breakdown include the seat, and the seat is listed in the summary the agent would confirm. | J50: Yes | K50: Never press 'Book' - it creates a real booking and takes money from the agency wallet. | Q50: Seat | S50: Approved
A51: 50 | B51: TC-SM-NEG-003 | C51: J. Errors and clashes | D51: Clicking quickly does not book two seats | E51: An impatient agent must not create a duplicate. | F51: Medium | G51: See the 'Before every test' sheet. | H51: 1. Click a seat. 2. Press the book button several times quickly. | I51: Only one seat is booked. The count never goes above the number of passengers, and the summary has no repeated lines. | J51: Yes | Q51: Seat | S51: Approved
A52: 51 | B52: TC-SM-NEG-004 | C52: J. Errors and clashes | D52: Two agents choosing the same seat at the same time | E52: Only one of them can really have it. | F52: High | G52: See the 'Before every test' sheet. You need two sessions open at once. | H52: 1. In two sessions, reach the seat map for the same flight. 2. Both choose the same seat. 3. Both go towards payment. | I52: Choosing a seat does NOT hold it. Both agents can choose and confirm the same seat with no error at that point. The clash is settled at the moment of booking: one booking works, the other fails with a message saying the seat is already taken. | J52: Partly | K52: The failure can only be seen by actually pressing 'Book', which this suite forbids. Run up to that point automatically and check the rest by hand in an approved booking window. Commented out 27 Sep 2026 (Mohanad Dawood): not to be executed. | M52: Commented out - not to be executed. | N52: Not to be executed | O52: Claude (run-006), for Mohanad Dawood | P52: 27 Sep 2026 | Q52: Seat | S52: Rejected
A53: 52 | B53: TC-SM-NEG-006 | C53: J. Errors and clashes | D53: Opening the booking page with a broken or missing link | E53: A tampered link must not give access to seats or prices. | F53: Medium | G53: See the 'Before every test' sheet. | H53: 1. Open the passenger details page with the security token missing, changed or expired. | I53: Access is refused and the agent is sent back to the flight search page - the same as when the time limit runs out. No seat map and no prices are shown, and no technical error page is shown to the agent. | J53: Yes | K53: The token lasts 60 minutes while testing and 15 minutes when live. | Q53: None | S53: Approved
A54: 53 | B54: TC-SM-A11Y-001 | C54: K. Small screens and screen readers | D54: The seat map works on a smaller screen | E54: The agent must still reach the last row of a long aircraft. | F54: Medium | G54: See the 'Before every test' sheet. | H54: 1. Open the seat map on a narrow window. 2. Scroll to the last row of the aircraft and book a seat there. | I54: The left panel and the seat chart both stay usable. The seat chart scrolls on its own without the whole page sliding sideways. Seats can still be clicked one by one, and the very last row can be reached and booked. | J54: Partly | K54: The mechanical parts can be checked automatically; whether it looks right needs a person. | Q54: Seat | S54: Approved
A55: 54 | B55: TC-SM-A11Y-002 | C55: K. Small screens and screen readers | D55: Seat states can be read by screen readers | E55: This also makes every automated check possible. | F55: Medium | G55: See the 'Before every test' sheet. | H55: 1. Check how free, taken and chosen seats are described to a screen reader, and how the book button is described. | I55: Each seat is a button with a description that includes whether it is available. Taken seats are announced as unavailable. The book button's description names the seat and the passenger. | J55: Yes | Q55: Seat | S55: Approved
A56: 55 | B56: TC-SM-CAB-001 | C56: L. Economy and Business | D56: The same flight gives a different map in each cabin | E56: The cabin changes the map completely, so every test must say which cabin it uses. | F56: Critical | G56: See the 'Before every test' sheet. You need the same flight bookable in both cabins. | H56: 1. Search the route in Economy, pick a flight and write down its whole map. 2. Do the same for the SAME flight in Business. 3. Compare. | I56: The two maps are clearly different. On flight XY-568 (174 seats): 161 seats bookable in Economy but only 4 in Business, and row 1 goes from fully blocked to being the only bookable row. Neither map is reused from the other. | J56: Yes | K56: Tagged 28 Sep 2026: needs a supplier that sells a second cabin. Air Cairo sells Economy only (cards read "No Business"), so these are excluded there. | Q56: Seat | R56: business-cabin | S56: Approved
A57: 56 | B57: TC-SM-CAB-002 | C57: L. Economy and Business | D57: The fare package decides WHICH seats are offered, not only their price | E57: Reading this as a price-only rule leads to wrong tests. | F57: Critical | G57: See the 'Before every test' sheet. | H57: 1. Note what the package says about seats ('Seat selection: All seats' or 'Premium' or 'Standard'). 2. Count how many seats can be booked and which parts of the aircraft they are in. | I57: The package changes both which seats are offered and what they cost. Seen so far: 'All seats' = 161 of 174, all free. 'Premium' = 4 of 174, free. 'Standard' = 156 of 174, 96 free and 60 paid. A package priced at zero is normal, not a missing price. Check the relationship, never the exact counts. | J57: Yes | K57: The Business figures came from the staging connection, which shows cabins wrongly - check them again on the live connection. Tagged 28 Sep 2026: needs a supplier that sells a second cabin. Air Cairo sells Economy only (cards read "No Business"), so these are excluded there. | Q57: Bundle + Seat | R57: business-cabin | S57: Approved
A58: 57 | B58: TC-SM-CAB-003 | C58: L. Economy and Business | D58: 'Not offered' sections can be told apart from single taken seats | E58: The agent needs to understand why a seat cannot be chosen. | F58: High | G58: See the 'Before every test' sheet. Use Business cabin with the 'Premium' package. | H58: 1. On a fare that only covers part of the aircraft, look at a section outside it. 2. Then look at a single taken seat inside the part you do have. | I58: The section header reads 'Not offered' and every seat in it cannot be chosen. This is CORRECT: a Business fare only covers the front section, so the Economy sections behind it are not part of that fare. Do not report it as missing seats. Careful: the same words 'Not offered' are ALSO used for a women-only seat shown to a male passenger. Check the section header here, and write down separately where the same words appear on a single seat. | J58: Partly | K58: Whether the agent should be able to tell the two reasons apart is still an open question for the business. Tagged 28 Sep 2026: needs a supplier that sells a second cabin. Air Cairo sells Economy only (cards read "No Business"), so these are excluded there. | Q58: Seat | R58: business-cabin | S58: Approved
A59: 58 | B59: TC-SM-CAB-004 | C59: L. Economy and Business | D59: The Business row has its middle seats blocked | E59: This is on purpose - it must not be reported as missing seats. | F59: Medium | G59: See the 'Before every test' sheet. Use Business cabin with the 'Premium' package. | H59: 1. On the one bookable row, check the state of every seat across the row. | I59: The middle seat of each group of three is blocked while the window and aisle seats are free (1B and 1E blocked; 1A, 1C, 1D, 1F free). This gives a 2 by 2 layout on an aircraft built 3 by 3, which is how Business is sold. | J59: Yes | K59: Seen on the staging connection, which shows cabins wrongly - check again on the live connection. Tagged 28 Sep 2026: needs a supplier that sells a second cabin. Air Cairo sells Economy only (cards read "No Business"), so these are excluded there. | Q59: Seat | R59: business-cabin | S59: Approved
A60: 59 | B60: TC-SM-CAB-005 | C60: L. Economy and Business | D60: Packages, meals and bags change with the cabin | E60: An agent must never be offered an extra the fare cannot carry. | F60: Medium | G60: See the 'Before every test' sheet. | H60: 1. Write down the packages, meals and extra bags offered in Economy. 2. Write down the same three lists for Business on the SAME flight. | I60: Each cabin has its own lists, none of them empty, and every package can be chosen. Economy offered: 'Plus', 'Light Super Flex', 'Value', 'Value Flex'. Business offered one package ('Premium') and one meal. Extra bags were the same in both. Check the lists fit the cabin - do not expect a fixed list. | J60: Yes | K60: Business half came from the staging connection - check again on the live connection. Tagged 28 Sep 2026: needs a supplier that sells a second cabin. Air Cairo sells Economy only (cards read "No Business"), so these are excluded there. | Q60: Bundle + Meal + Baggage | R60: business-cabin | S60: Approved
A61: 60 | B61: TC-SM-CAB-007 | C61: L. Economy and Business | D61: A two-cabin aircraft shows both cabins properly | E61: We have never been able to confirm the Business cabin is labelled as Business. | F61: High | G61: See the 'Before every test' sheet. THIS TEST NEEDS THE LIVE CONNECTION - it cannot be done on staging. | H61: 1. On the live connection, open the seat map of a flight sold in two cabins. 2. Check the cabin name on the seats at the front, the colour key and the prices. | I61: The front section is marked as BUSINESS, with its own entry in the colour key and its own price, while the sections behind it are marked Economy. On staging every section is wrongly marked 'Economy', including the Business one - that is a staging data problem, not a system fault, and must not be reported as one. | J61: No | K61: Waiting for the live connection. The two-cabin structure is already visible (front section bookable, rest 'Not offered') - only the cabin NAME is wrong on staging. Tagged 28 Sep 2026: needs a supplier that sells a second cabin. Air Cairo sells Economy only (cards read "No Business"), so these are excluded there. | Q61: Seat | R61: business-cabin | S61: Approved
A62: 61 | B62: TC-SM-PAX-001 | C62: M. Adults, children and infants | D62: Infants get no seat and no extras; children get both | E62: The seat count and the extras offered must match airline policy. | F62: Critical | G62: See the 'Before every test' sheet. Book 1 adult + 1 child + 1 infant. | H62: 1. Search for 1 adult, 1 child and 1 infant and complete step 1. 2. Look at step 2. 3. Open the seat map, read the count, and give the child a seat. 4. Confirm and read the summary. | I62: Step 2 shows extras for the ADULT AND CHILD ONLY - the infant appears nowhere: no meal, no bag, no seat. The seat count reads 0 of 2 even though there are 3 passengers. The child can be given a seat, and the summary says '2 travellers'. | J62: Yes | K62: Checked again on 15 Sep 2026 - unchanged. | Q62: Seat | S62: Approved
A63: 62 | B63: TC-SM-PAX-003 | C63: M. Adults, children and infants | D63: An infant must be linked to an adult | E63: The exit-seat rule depends on this link. | F63: High | G63: See the 'Before every test' sheet. Book 1 adult + 1 child + 1 infant. | H63: 1. On step 1, open the infant's 'Assigned to' list. 2. Look at the options. | I63: The 'Assigned to' box appears only for the infant and must be filled in. Only ADULTS are listed - the child cannot be chosen as the person responsible for the infant. | J63: Yes | Q63: None | S63: Approved
A64: 63 | B64: TC-SM-PAX-004 | C64: M. Adults, children and infants | D64: The map moves on to the next passenger automatically | E64: A group can be seated one after another without extra clicks. | F64: Medium | G64: See the 'Before every test' sheet. Book 1 adult + 1 child + 1 infant. | H64: 1. With 2 passengers who can have seats, give a seat to the first. 2. See which passenger card is now selected, then click another seat. | I64: The next passenger without a seat becomes the selected one automatically, so the next seat you click goes to them, and the book button names them. A passenger who already has a seat shows as SELECTED when they are the active one, and ASSIGNED when they are not. | J64: Yes | Q64: Seat | S64: Approved
A65: 64 | B65: TC-SM-PAX-006 | C65: M. Adults, children and infants | D65: Each passenger type is priced separately | E65: Protects the total on family bookings. | F65: Medium | G65: See the 'Before every test' sheet. Book 1 adult + 1 child + 1 infant. | H65: 1. Read the price breakdown for each passenger type. 2. Read the baggage allowance for each passenger type. | I65: The fare and tax are listed for each passenger type. Seen in Business: the adult and the child cost EXACTLY THE SAME (8,906 fare + 8,205 tax each); the infant paid 4,231 with no tax. Do NOT assume a child is cheaper - on this airline they are not. The infant's baggage reads 'Check with Airline'. | J65: Yes | Q65: None | S65: Approved
A66: 65 | B66: TC-SM-PAX-007 | C66: M. Adults, children and infants | D66: Closed passenger sections still report missing information | E66: An agent must never be stuck with no visible reason. | F66: Low | G66: See the 'Before every test' sheet. Book 1 adult + 1 child + 1 infant. | H66: 1. Close a passenger's section and try to type in its boxes. 2. Use 'Expand All' and 'Collapse All'. 3. Press 'Next' with a closed, incomplete passenger. | I66: A closed section cannot be typed into, and 'Expand All' opens it again. Only one passenger section is open at a time. If a closed passenger is incomplete, pressing 'Next' still reports it clearly. | J66: Yes | L66: Passengers are p-accordiontab elements inside .pax-form-accordion. A script must open a section before filling it, or the typing silently does nothing. | Q66: None | S66: Approved
A67: 66 | B67: TC-SM-FRC-001 | C67: N. Price change before booking | D67: A changed price is shown before the booking screen | E67: Agents quote the search price, so an increase must never be silent. | F67: High | G67: See the 'Before every test' sheet. Include an INFANT in the search - that is what triggers the price change. | H67: 1. Search with an infant in the party and pick a flight. 2. Press 'Book Flight'. 3. Read the pop-up and open its details. | I67: A 'Price Update' pop-up appears BEFORE the booking screen, saying the airline has changed the price. It shows the old and new price, the flight details, the fare for each passenger type, any penalties, a countdown to confirm, and Cancel / Accept buttons. Searching WITHOUT an infant should not produce the pop-up. | J67: Yes | K67: Known behaviour, not a fault. It happens when an infant is in the party. Seen: 36,072 becoming 38,453 EGP with about 4 minutes to confirm. | Q67: None | S67: Approved
A68: 67 | B68: TC-SM-FRC-002 | C68: N. Price change before booking | D68: Accepting the new price carries it forward | E68: The booking must be priced at the figure actually agreed. | F68: High | G68: See the 'Before every test' sheet. The 'Price Update' pop-up must be showing. | H68: 1. Press 'Accept'. 2. Check the amount to pay on the next screen. | I68: You move on to the booking screen, and the amount to pay equals the NEW accepted price, not the old search price. | J68: Partly | K68: Needs a price change to happen first. | L68: The security token carries fareMismatch: true after a price change (false when there was none). | Q68: None | S68: Approved
A69: 68 | B69: TC-SM-FRC-003 | C69: N. Price change before booking | D69: Cancelling leaves nothing behind | E69: No booking, no money moved. | F69: High | G69: See the 'Before every test' sheet. The 'Price Update' pop-up must be showing. | H69: 1. Press 'Cancel'. 2. Check the results list, the wallet balance and the bookings list. | I69: You go back to the results list. No booking was made, no money moved in the wallet, and the agent can pick another flight. | J69: Partly | K69: Needs a price change to happen first. | Q69: None | S69: Approved
A70: 69 | B70: TC-SM-FRC-005 | C70: N. Price change before booking | D70: Every later total uses the accepted price | E70: The old price must never come back. | F70: High | G70: See the 'Before every test' sheet. A price change must have been accepted. | H70: 1. After accepting, read the total on the fare package step, the extras step and the payment screen. | I70: Every total is worked out from the new accepted price. The old search price appears nowhere. | J70: Partly | K70: Needs a price change to happen first. | Q70: None | S70: Approved
A71: 70 | B71: TC-SM-ERR-001 | C71: O. System problems | D71: A server failure must not look like 'No Flights Found' | E71: Agents would chase a problem that does not exist. | F71: High | G71: See the 'Before every test' sheet. | H71: 1. Run a search while watching the browser network tab. 2. Compare the technical status with the message on screen. 3. Run the same search again. | I71: If the server fails, the screen should show an ERROR with a way to retry - not 'No Flights Found'. What actually happens: the server returned an error while the screen said 'No Flights Found'. The business has accepted this as known behaviour, so do NOT report it as a fault. Keep the check running in the background so we notice if it gets worse. | J71: No | K71: Accepted by the business on 17 Sep 2026. It happens only sometimes and cannot be made to happen on demand. | Q71: None | S71: Approved
A72: 71 | B72: TC-SM-ERR-002 | C72: O. System problems | D72: The session ending in the middle of a booking | E72: Losing a half-filled family booking is painful for the agent. | F72: Medium | G72: See the 'Before every test' sheet. Book 1 adult + 1 child + 1 infant. | H72: 1. Fill in details for all passengers. 2. Leave the session until it expires (about 10 to 12 minutes was enough). 3. Press 'Next'. | I72: You are sent to the login page with 'Session has been expired. Please login again'. What actually happens: everything typed in is lost. Ask the business whether losing a part-filled form is acceptable, or whether it should be kept. | J72: Yes | Q72: None | S72: Approved
A73: 72 | B73: TC-SM-ERR-004 | C73: O. System problems | D73: Typing in one dropdown must not affect another | E73: The agent could believe a list is much shorter than it is. | F73: Low | G73: See the 'Before every test' sheet. | H73: 1. Type into one dropdown (for example nationality) to narrow it down, and pick a value. 2. Open a DIFFERENT dropdown of the same kind. | I73: The second dropdown opens empty with the full list. What actually happened: the second nationality list opened still filtered to 'egy' and showed only one option. | J73: Yes | Q73: None | S73: Approved
A74: 73 | B74: TC-SM-ERR-005 | C74: O. System problems | D74: Each offer says which airline connection it came from | E74: A price from the test connection must be recognisable. | F74: Low | G74: See the 'Before every test' sheet. Admin is at http://192.168.1.70. | H74: 1. Look at the connection name on each result card. | I74: Each card names its connection, for example 'Fly Nas NDC EGY Staging (NO WARNING)' or 'Fly Nas KSA PRODUCTION (WARNING)'. IMPORTANT: the staging connection is now known to report cabins wrongly, so every price, seat and cabin recorded from it must be checked again on the live connection. | J74: Yes | Q74: None | S74: Approved
A75: 74 | B75: TC-SM-EXR-001 | C75: P. Emergency exit seats | D75: An adult travelling alone CAN take an exit seat | E75: Without this, the other exit-seat tests could pass for the wrong reason. | F75: High | G75: See the 'Before every test' sheet. Use a fare that actually offers the exit rows (Economy 'Plus', not Business 'Premium'). Book one adult with no infant. | H75: 1. Open the seat map and find a seat marked 'Exit and emergency exit'. 2. Click it. 3. Book it. | I75: The seat is available, the book button works, and the seat is booked. Run this first - it proves the refusals in the next tests actually mean something. | J75: Yes | Q75: Seat | S75: Approved
A76: 75 | B76: TC-SM-EXR-002 | C76: P. Emergency exit seats | D76: An adult with an infant CANNOT take an exit seat | E76: This is an airline safety rule and must never be broken. | F76: Critical | G76: See the 'Before every test' sheet. Use a fare that offers the exit rows. Book 1 adult + 1 infant, with the infant linked to that adult on step 1. | H76: 1. Open the seat map with the adult selected. 2. Click a seat marked 'Exit and emergency exit'. 3. Try to book it. | I76: The adult cannot take the seat - it shows as unavailable, or the book button is greyed out. The agent should be able to understand why. A bare 'Blocked' with no explanation is worth reporting even though the refusal itself is correct. | J76: Yes | Q76: Seat | S76: Approved
A77: 76 | B77: TC-SM-EXR-003 | C77: P. Emergency exit seats | D77: A child CANNOT take an exit seat | E77: The second half of the exit-seat safety rule. | F77: Critical | G77: See the 'Before every test' sheet. Use a fare that offers the exit rows. Book an adult and a child. | H77: 1. Open the seat map and select the CHILD. 2. Click a seat marked 'Exit and emergency exit'. 3. Try to book it. 4. Switch to the adult and click the same seat. | I77: The child cannot take the seat, but the adult still can. This proves the rule applies to the passenger, not to the whole flight. | J77: Yes | K77: Stated by the business, not yet checked in this system. | Q77: Seat | S77: Approved
A78: 77 | B78: TC-SM-EXR-004 | C78: P. Emergency exit seats | D78: The rule is rechecked when you switch passenger | E78: The most valuable test here - a map worked out once per flight would let the wrong passenger into an exit seat. | F78: Critical | G78: See the 'Before every test' sheet. Use a fare that offers the exit rows. Book an adult and a child. | H78: 1. With the ADULT selected, check an exit seat can be booked (do not book it). 2. Switch to the CHILD. 3. Look at the SAME seat again. | I78: The same seat changes from bookable to not bookable, only because the selected passenger changed. | J78: Yes | Q78: Seat | S78: Approved
A79: 78 | B79: TC-SM-EXR-005 | C79: P. Emergency exit seats | D79: The rule follows the infant's linked adult | E79: It must follow the link, not just block every adult on the booking. | F79: High | G79: See the 'Before every test' sheet. Use a fare that offers the exit rows. Book 2 adults + 1 infant, linked to adult A. | H79: 1. Check an exit seat as adult A and then as adult B. 2. Go back to step 1 and link the infant to adult B instead. 3. Return to step 2 and check the same seat as both adults. | I79: At first the seat is refused for A and allowed for B. After the change the refusal MOVES: A can now take it and B cannot. The rule follows the 'Assigned to' link, not just the presence of an infant on the booking. | J79: Yes | Q79: Seat | S79: Approved
A80: 79 | B80: TC-SM-EXR-007 | C80: P. Emergency exit seats | D80: An exit seat already taken is dealt with when an infant is added later | E80: The highest-risk failure in this whole suite. | F80: High | G80: See the 'Before every test' sheet. Use a fare that offers the exit rows. Book an adult, then add the infant afterwards. | H80: 1. Give the adult an exit seat and confirm it. 2. Go back to step 1 and link an infant to that adult. 3. Return to step 2 and look at the seat they hold. | I80: The seat must NOT quietly stay. Either it is taken away with a clear message, or the agent is made to choose another seat. An adult holding an exit seat with an infant on their lap would break an airline safety rule, and it would reach the airline. | J80: Yes | K80: Commented out 27 Sep 2026 (Mohanad Dawood): not to be executed. | M80: Commented out - not to be executed. | N80: Not to be executed | O80: Claude (run-006), for Mohanad Dawood | P80: 27 Sep 2026 | Q80: Seat | S80: Rejected
A81: 80 | B81: TC-SM-RTP-001 | C81: S. Seat map on return and multi-city trips | D81: A return trip gives one seat map per journey | E81: The seat map is drawn once per journey, not once per booking. | F81: Critical | G81: See the 'Before every test' sheet. | H81: 1. Search a return trip and reach the ancillaries step. 2. Count the 'Select Seat' buttons and open each map. | I81: There is one seat map per journey, each titled with its own direction, and each showing its own aircraft. | J81: Yes | K81: Return flights do exist on this server (298 options on 19 Sep 2026); an older note saying otherwise is out of date. | L81: Read the number of journeys from the search and assert that many maps. Do not hard-code 2. | Q81: Seat | S81: Approved
A82: 81 | B82: TC-SM-RTP-003 | C82: S. Seat map on return and multi-city trips | D82: Each journey's fare package sets that journey's seat prices | E82: Seat pricing follows the package chosen for THAT journey only. | F82: Critical | G82: See the 'Before every test' sheet. | H82: 1. Give each journey a DIFFERENT fare package - at least one that charges for seats and one that does not. 2. Open each journey's seat map and count free seats, paid seats and price tiers. | I82: Each journey's seat prices follow its own package. Changing one journey's package must not change another journey's seat prices. | J82: Yes | K82: Proved 19 Sep 2026 holding three packages at once: 'Value' gave 95 free / 35 at 422.91 / 29 at 1097.91, while 'Plus' on the SAME booking gave 162 free and no paid seats at all. Replaces old test 37, which could never be run. | L82: The cleanest single proof that the fare package drives seat prices. Run every release. | Q82: Bundle + Seat | S82: Approved
A83: 82 | B83: TC-SM-RTP-004 | C83: S. Seat map on return and multi-city trips | D83: Seat maps are completely separate per journey | E83: A seat chosen on one journey must never appear on another. | F83: Critical | G83: See the 'Before every test' sheet. | H83: 1. Choose and confirm a seat on journey 1. 2. Open journey 2's seat map. | I83: Journey 2's map opens with nothing chosen, on its own aircraft, and the seat number used on journey 1 is still offered there. Only journey 1's button changes to 'Change Seats'. | J83: Yes | K83: Proved 19 Sep 2026: after booking 14B on leg 1, leg 2 opened on a different aircraft (172 seats vs 174) and 14B there still read 'available for Free'. | L83: This is the test that catches seat data leaking between journeys. | Q83: Seat | S83: Approved
A84: 83 | B84: TC-SM-MCT-003 | C84: S. Seat map on return and multi-city trips | D84: Three journeys give three seat maps and three sets of ancillaries | E84: The per-journey rule is not hard-coded to 'outbound and return'. | F84: Critical | G84: See the 'Before every test' sheet. | H84: 1. Build a multi-city trip with at least 3 legs and reach the ancillaries step. 2. Count the seat maps, the meal boxes and the baggage panels. | I84: One seat map per flight, each titled with its own route, and ancillary panels to match. | J84: Yes | K84: Verified on Cairo-Jeddah-Riyadh-Cairo: three 'Select Seat' buttons opening maps titled Trip 1 / Trip 2 / Trip 3. | L84: Do not hard-code 3 - read the itinerary and assert that many. | Q84: Seat | S84: Approved
A85: 84 | B85: TC-SM-MCT-004 | C85: S. Seat map on return and multi-city trips | D85: A seat booked on one flight never appears against another | E85: Seats stay attached to their own flight all the way to the ticket. | F85: Critical | G85: See the 'Before every test' sheet. | H85: 1. Give seats to passengers on several flights. 2. Check the summary, the confirmation page and the e-ticket. | I85: Each seat appears against its own flight only, for the passenger who booked it, with that flight's price. | J85: Yes | K85: Confirmed end to end on 19 Sep 2026 (booking S6GUFL): eight seats across four flights all landed correctly. | L85: Match passenger + flight + seat number together, not just the set of seats. | Q85: Seat | S85: Approved
A86: 85 | B86: TC-SM-MCT-007 | C86: S. Seat map on return and multi-city trips | D86: Seat maps follow FLIGHTS, fare packages follow JOURNEYS | E86: When a journey has a connection there are more seat maps than fare packages. | F86: Critical | G86: See the 'Before every test' sheet. | H86: 1. Build a multi-city where at least ONE journey connects (for example Jeddah to Riyadh via Dammam). 2. Count fare-package boxes, then count seat maps and meal boxes. | I86: Fewer fare packages than seat maps. With 3 journeys and 4 flights: 3 fare packages, but 4 seat maps, 4 baggage tabs and 8 meal boxes (4 flights x 2 eligible passengers). Both flights of the connecting journey inherit that journey's single package - an all-seats-free package makes seats free on BOTH. | J86: Yes | K86: Verified 19 Sep 2026. This corrects an earlier belief that there was one map per journey. | L86: This test MUST use a connecting journey - a non-stop trip cannot tell a journey and a flight apart. | Q86: Seat | S86: Approved
A87: 86 | B87: TC-SM-MCT-005 | C87: S. Seat map on return and multi-city trips | D87: Seats and ancillaries survive to the confirmation page per flight | E87: Nothing is lost or re-attributed between the booking screen and the ticket. | F87: High | G87: See the 'Before every test' sheet. | H87: 1. Complete a multi-trip booking with seats and ancillaries on several flights. 2. Compare the confirmation page and e-ticket against what was chosen. | I87: Every seat and every ancillary appears against the right flight for the right passenger, and the total is the sum across all journeys. | J87: Yes | K87: PASSED 19 Sep 2026 (S6GUFL): 3 journeys, 4 flights, 8 meals, 8 seats and 2 bags all carried through correctly. | L87: Only run the booking half under the section Q money rules. | Q87: Seat | S87: Approved
A88: 87 | B88: TC-SM-MCT-006 | C88: S. Seat map on return and multi-city trips | D88: Extra baggage should say which flight it belongs to | E88: An agent must be able to tell which leg a bag is being bought for. | F88: Critical | G88: See the 'Before every test' sheet. | H88: 1. Build a 3-leg multi-city and reach the ancillaries step. 2. Count the 'Extra Baggage' panels, then open the list and read every option. | I88: One baggage panel per journey, or at minimum every option names its journey. KNOWN FAULT: there is ONE panel headed 'Trip 1' holding all twelve options from all three journeys, unlabelled - and some are identical in BOTH name and price. | J88: Yes | K88: Meals and seats DO show one panel per flight on the same page, so the fault is specific to baggage. The system books them against the CORRECT journey - a labelling fault, not a mis-sale. | L88: Root cause is the ssr-quote response shape: meals come back as a list per route, baggage as single onwardJourney/returnJourney objects. | Q88: Baggage | S88: Approved
A89: 88 | B89: TC-SM-RTP-005 | C89: S. Seat map on return and multi-city trips | D89: Seat and ancillary charges should be identifiable per journey | E89: An agent needs to know what each leg's seats and extras cost. | F89: High | G89: See the 'Before every test' sheet. | H89: 1. Buy seats and ancillaries on more than one journey. 2. Read the price breakdown panel. | I89: Each journey's charges are identifiable. KNOWN FAULT: they are not - one merged fare-package line, one base fare line and one tax line covered three journeys. | J89: Yes | K89: The grand total is CORRECT; only the breakdown is too coarse. A reporting gap, not a pricing fault. | L89: Assert that a per-journey breakdown exists. Expect this to fail until fixed. | Q89: Seat | S89: Approved
A90: 89 | B90: TC-SM-CNF-001 | C90: Q. Completing the booking (SPENDS REAL MONEY) | D90: The confirmation total equals what was quoted | E90: The customer is charged what the agent quoted. | F90: Critical | G90: See the 'Before every test' sheet. | H90: 1. Write down 'Net Payable' on the payment panel. 2. Press 'Book'. 3. Read the confirmation total. | I90: Rounded UP, the quoted figure equals the confirmation total. Money always rounds up, at any fraction. | J90: Yes | K90: PASSED on S6GUFL: quoted 61,257, confirmation 61,257, e-ticket 61,257 - exact. | L90: Assert ceiling(quoted) == confirmation. NEVER use a plus/minus tolerance. | Q90: None | S90: Approved
A91: 90 | B91: TC-SM-CNF-002 | C91: Q. Completing the booking (SPENDS REAL MONEY) | D91: Every price line survives the booking unchanged | E91: No price line is added, dropped or altered by booking. | F91: Critical | G91: See the 'Before every test' sheet. | H91: 1. Compare the confirmation's price lines against the snapshot taken before paying. | I91: The same lines with the same amounts. The confirmation ADDS UP base fare and tax across passenger types into one line each, where the booking screen listed them per passenger type. | J91: Yes | K91: Compare the SUM of the per-passenger lines against the single confirmation line - not row by row. Verified on S6GUFL: base 14,944, tax 18,026. | L91: A sum comparison, not a row match. | Q91: None | S91: Approved
A92: 91 | B92: TC-SM-CNF-003 | C92: Q. Completing the booking (SPENDS REAL MONEY) | D92: Every ancillary reaches the confirmation with its own price | E92: Meals, bags, seats and the fare package each survive with their charge. | F92: Critical | G92: See the 'Before every test' sheet. | H92: 1. Compare each ancillary line on the confirmation with what was chosen. | I92: Meal, Extra Baggage, Seat and Bundle each appear as their own priced line, matching what was chosen. | J92: Yes | K92: PASSED on S6GUFL: Meal 3,920, Seat 6,672, Baggage 6,965, Bundle 10,730. | L92: Per-item prices for meals and seats are deliberately NOT shown per row - only the totals. Do not assert per-row prices for those two. | Q92: None | S92: Approved
A93: 92 | B93: TC-SM-CNF-004 | C93: Q. Completing the booking (SPENDS REAL MONEY) | D93: Seats carry through to the right passenger with the right price | E93: No seat moves to another passenger, disappears or changes price. | F93: Critical | G93: See the 'Before every test' sheet. | H93: 1. Check every confirmed seat on the confirmation against who booked it. | I93: Every seat appears against the passenger who booked it, on its own flight; a free seat reads free and a paid seat carries its charge. | J93: Yes | K93: PASSED on S6GUFL with 8 seats across 4 flights for 2 passengers. | L93: Match passenger + flight + seat number together. | Q93: Seat | S93: Approved
A94: 93 | B94: TC-SM-CNF-007 | C94: Q. Completing the booking (SPENDS REAL MONEY) | D94: Infants appear as passengers but carry no seat or ancillaries | E94: An infant has a fare but no seat, meal or bag. | F94: High | G94: See the 'Before every test' sheet. | H94: 1. Book with an infant. 2. Check the infant's row on the confirmation, and the booked-seat count. | I94: The infant shows '-' for meal, seat and package, and has no ancillary panel at all. The advertised seat count must equal the seats actually held. | J94: Yes | K94: KNOWN FAULT: the overview claimed '3 Booked Seats' for a booking holding 2, counting the seatless infant. 27 Sep 2026 (run-006, PNR VYHQKP): known fault reproduced - the counter counts passengers, not seats. Confirmed bug, low priority. | L94: Assert the advertised seat count against the seats actually assigned. | M94: Infant row correct ('-' for meal, seat and package, no ancillary panel). All 4 seats correct. But the order page overview says '3 Booked Seats' for a booking holding 2 per flight; a failed booking with no seat said '1 Booked Seats'. | N94: Fail | O94: Claude (run-006), for Mohanad Dawood | P94: 27 Sep 2026 | Q94: None | S94: Approved
A95: 94 | B95: TC-SM-CNF-008 | C95: Q. Completing the booking (SPENDS REAL MONEY) | D95: The e-ticket and the confirmation page agree exactly | E95: The document handed to the traveller matches the booking record. | F95: Critical | G95: See the 'Before every test' sheet. | H95: 1. Open the e-ticket. 2. Compare it against the confirmation page field by field. | I95: Booking reference, PNR, flights, routes, dates, times, cabin, every passenger, every seat, every ancillary and every price line are identical. Nothing is re-calculated or re-rounded. | J95: Yes | K95: PASSED twice, most recently S6GUFL - all 8 meals, all 8 seats, both bags with their legs and all six price lines matched, total 61,257. | L95: A pure comparison - cheap to automate, very high value. | Q95: None | S95: Approved
A96: 95 | B96: TC-SM-CNF-010 | C96: Q. Completing the booking (SPENDS REAL MONEY) | D96: The wallet is reduced by exactly the booking amount | E96: The money that leaves the wallet matches the money billed. | F96: Critical | G96: See the 'Before every test' sheet. | H96: 1. Record the wallet balance before booking. 2. Book. 3. Record it after. 4. Compare the difference with the booking total. | I96: Balance before minus balance after equals the booking total, exactly. | J96: Yes | K96: PASSED on S6GUFL: 387,553.428 - 326,296.428 = 61,257.000 against a total of 61,257. ONE OLDER CASE REMAINS UNEXPLAINED: on a fare with fractional prices the wallet moved 0.73 LESS than the record - re-run this deliberately on such a fare. 27 Sep 2026 (run-006): the Statement shows the right debit (20,737.00) but its balance moved 20,735.38. Rule engine off made no difference. Supplier credential is SAR at ROE 9 and all prices match 9 exactly; the wallet behaves as if a slightly different rate (about 9.001-9.003) were used. Needs the wallet transaction record to confirm. | L96: The single most important test in this section. | M96: Prices are right: every line adds up and the total is that sum rounded up. But the wallet dropped less than the total on 3 of 3 bookings: 20,737 vs 20,735.36; 4,264 vs 4,262.78; 3,913 vs 3,911.60. | N96: Fail | O96: Claude (run-006), for Mohanad Dawood | P96: 27 Sep 2026 | Q96: None | S96: Approved
A97: 96 | B97: TC-SM-CNF-011 | C97: Q. Completing the booking (SPENDS REAL MONEY) | D97: The Costing tab adds up and is the figure to trust | E97: The Costing tab is the authoritative amount. | F97: High | G97: See the 'Before every test' sheet. | H97: 1. Open the booking's Costing tab. 2. Add the per-passenger totals plus the total ancillary amount. | I97: The parts add up to the Total Booking Amount, and Total Booking equals Total Sales equals Total Net when no markup or discount is configured. | J97: Yes | K97: This tab was the only surface that added up in the earlier fractional-priced booking. | L97: Use as the reference figure the other money tests are measured against. | Q97: None | S97: Approved
A98: 97 | B98: TC-SM-CNF-012 | C98: Q. Completing the booking (SPENDS REAL MONEY) | D98: The order page itemises every ancillary and reconciles | E98: The full breakdown is available on the order page. | F98: Critical | G98: See the 'Before every test' sheet. | H98: 1. Open the order's details page and read the 'Fare Details' block. 2. Separately read the 'Total' column in the My Bookings LIST. | I98: 'Fare Details' shows Base fare, Taxes and a line per ancillary bought, and its Total matches the quote and the wallet. The LIST 'Total' column is fare-only (base + tax) BY DESIGN - do not compare it with the amount charged. | J98: Yes | K98: Corrected 19 Sep 2026 - an earlier version wrongly treated the fare-only list column as a fault. 27 Sep 2026 (run-006, PNR VYHQKP): order totals are correct; the only mismatch is the wallet (same cause as TC-SM-CNF-010). List 'Total' 13,140.36 = base + tax, fare-only as designed. | L98: Two different assertions against two different screens. | M98: Fare Details lists Base, Taxes, Meal, Seat, Baggage and Bundle correctly, total 20,737 = the exact sum rounded up. It does not match the wallet movement (20,735.36). The Portal order-details page has no 'Fare Details' block - it is on the confirmation page. | N98: Fail | O98: Claude (run-006), for Mohanad Dawood | P98: 27 Sep 2026 | Q98: None | S98: Approved
A99: 98 | B99: TC-SM-CNF-015 | C99: Q. Completing the booking (SPENDS REAL MONEY) | D99: Walking away before 'Book' creates nothing - THE SAFE TEST | E99: An abandoned booking leaves no order and takes no money. | F99: High | G99: See the 'Before every test' sheet. | H99: 1. Fill everything in, choose seats and ancillaries. 2. Do NOT press 'Book'. Close the page or let the offer expire. 3. Check My Bookings and the wallet. | I99: No order exists and the wallet is unchanged. | J99: Yes | K99: THE ONLY TEST IN SECTION Q THAT COSTS NOTHING - safe in any regression sweep. | L99: Run this one freely. | Q99: None | S99: Approved
A100: 99 | B100: TC-SM-CNF-016 | C100: Q. Completing the booking (SPENDS REAL MONEY) | D100: Extra baggage must not clash with the baggage already in the fare package | E100: A combination the airline will reject must never be sellable. | F100: Critical | G100: See the 'Before every test' sheet. | H100: 1. Choose a fare package that already includes checked baggage (for example '30KG Check-in Baggage'). 2. Buy extra baggage of the SAME weight for that passenger on that leg. 3. Complete the booking. | I100: Either the clashing option is not offered, or the agent is warned BEFORE paying. KNOWN FAULT: it is offered, priced, and the booking then fails at the airline. | J100: Yes | K100: Failed with 'SSR (PDBG) is restricted to 1 occurence(s) per passenger and leg'. Changing that passenger from 30Kg to 25Kg, nothing else changed, booked successfully. One leg's package used a different code (15KG BULK) and never clashed - so this WILL look intermittent. 27 Sep 2026 (run-006): Pass by decision - supplier behaviour, like the exit rows. The Portal does not block the clash; the airline rejects the booking. | L100: FOR THE AUTOMATION TEAM: read the package contents first and pick a DIFFERENT weight, unless deliberately testing this. | M100: With 'Value' (includes 30KG PDBG) the 30Kg extra bag was offered at 5,310 EGP with no warning. The airline rejected the booking: 'SSR (PDBG) is restricted to 1 occurence(s) per passenger and leg.' Wallet not charged. | N100: Pass | O100: Claude (run-006), for Mohanad Dawood | P100: 27 Sep 2026 | Q100: Baggage | S100: Approved
...

Sheet Before every test
A1: Before every test - read this once
A4: Where | B4: Admin panel at http://192.168.1.70 - Booking-Mid Office - Flight Search.
A5: Who | B5: Log in as the admin user, then choose the branch, the agency and the agent before searching. Nothing works until all three are chosen.
A6: What to search | B6: Branch BRN298, Cairo (CAI) to Jeddah (JED), 1 adult + 1 child + 1 infant, unless a test says otherwise. The travel date must be in the future - update it when it passes.
A7: NEVER press 'Book' | B7: Pressing 'Book' creates a REAL booking and takes real money from the agency wallet. Stop at the payment screen, or use 'Save Quote'.
A8: Two steps | B8: Step 1 is 'Passenger Info and Bundles' - passenger details and the fare package. Step 2 is 'Ancillaries' - meals, bags and seats. There is no third step.
A10: Words used in this sheet
A11: fare package (bundle) | B11: The fare option you pick on step 1, such as 'Plus' or 'Value'. It decides which seats you get and whether they cost extra.
A12: extras (ancillaries) | B12: Meals, extra bags and seats - everything on step 2.
A13: left panel | B13: The strip down the left of the seat map showing the flight, the seat total and the passenger cards.
A14: seat chart | B14: The drawing of the aircraft with all the seats.
A15: colour key | B15: The box headed 'What the plan shows' that explains the seat colours.
A16: section | B16: A named block of rows, such as Y-1 or Y-2. Each section has its own price written above it.
A17: seats-chosen count | B17: The '0 of 2' counter showing how many passengers have a seat so far. Infants are never counted.
A19: Important rule for writing tests
A20: Never fix a row or seat number | B20: Every flight uses a different aircraft, so the rows, seats, totals and prices change. Always find a seat by what it is marked with, and check that numbers agree with each other - never that they equal a particular figure.
A21: Say which cabin and package | B21: The same flight gives a completely different map in Economy and Business, and a different one again for each fare package. A test that does not say which it used cannot be repeated.
A22: Staging warning | B22: The airline connection in use is the test one ('Fly Nas NDC EGY Staging'). It reports cabins wrongly. Prices, cabins and seat availability seen here must be checked again on the live connection.
A24: Every booking run needs FRESH passenger names and document numbers.
A25: The system refuses a second booking for a passenger whose name, date of birth and document already have one. It returns a clear message that is NEVER shown on screen, so the booking simply appears to do nothing. This is not a seat-map test - it is a constraint on how the tests are run.

Sheet Questions for the business
A1: Questions for the business
A3: Most questions were answered on 17 Sep 2026. Only the ones still open need a decision. An unanswered question does not stop a test running - run it, write down what happened, and do not mark it failed.
A5: Question | B5: Answer / status | C5: What it means for testing
A6: Is a seat marked 'Chargeable seat' but priced Free a mistake? | B6: ANSWERED, THEN CORRECTED - a chargeable seat must ALWAYS be paid. It can never be free. | C6: Test 32 now reports a fault if such a seat shows as free. The free seat seen under 'Plus' on 09 Sep is a defect.
A7: What happens when the time limit runs out? | B7: ANSWERED - the agent is sent back to the flight search page. The limit is 60 minutes for testing and 15 minutes when live. | C7: Tests 48 and 52. Do not write 60 minutes into any test; re-run both before go-live.
A8: Is a seat held as soon as it is chosen? | B8: ANSWERED - no. Two agents can both choose it. The clash is settled at booking: one succeeds, the other is told the seat is taken. | C8: Test 51 can only be finished by really pressing 'Book', which needs approval.
A9: Why does a Business fare show every section as Economy? | B9: ANSWERED - it is a staging data problem, not a system fault. It does not happen on the live connection. | C9: Test 60 waits for the live connection. Do not report the wrong cabin name as a fault.
A10: Should the agent be able to tell WHY a seat cannot be chosen? | B10: STILL OPEN - needs a decision. | C10: A seat can be unavailable for four reasons but the screen shows only two messages. See the table below.
A11: Is the price change between search and booking expected? | B11: ANSWERED - yes, known behaviour. It happens when an infant is in the party. | C11: Test 66 uses an infant to make it happen on purpose.
A12: Are children under the same seat rules as adults? | B12: ANSWERED - yes, for both exit seats and women-only seats. | C12: Tests 45 and 74-79.
A13: Which passengers cannot sit in an exit seat? | B13: ANSWERED - two kinds only: an adult who has an infant with them, and a child. | C13: Tests 74 to 79. Still to check: at which point the system stops them.
A14: How is a seat taken by another passenger in the same booking shown? | B14: ANSWERED as 'Blocked' - but what we actually saw also NAMES the passenger holding it. | C14: Tests 26 and 28 expect the named version. Please confirm which is intended.
A15: A server error is shown as 'No Flights Found'. Is that acceptable? | B15: ACCEPTED - known behaviour, will not be reported as a fault. | C15: Test 70 stays as a background check only.
A16: The airline connection in use is the test one. Does that matter? | B16: STILL OPEN - and it does matter: it reports cabins wrongly. | C16: Every price, cabin and seat figure must be checked again on the live connection.
A19: Why a seat cannot be chosen - four reasons, two messages
A20: What is really true | B20: What the agent sees
A21: This part of the aircraft is not in your fare | B21: Not offered
A22: This seat is kept for women and your passenger is male | B22: Not offered
A23: Somebody else has this seat | B23: Blocked
A24: Another passenger in YOUR booking has this seat | B24: Shown as held, and it names them

Sheet Summary
A1: Summary
A3: Tests in this sheet | B3: 79
A5: By priority | C5: Passed
A6: Critical | B6: 15 | C6: =COUNTIFS('Test Cases'!$F$2:$F$80,$A6,'Test Cases'!$N$2:$N$80,"Pass")
A7: High | B7: 41 | C7: =COUNTIFS('Test Cases'!$F$2:$F$80,$A7,'Test Cases'!$N$2:$N$80,"Pass")
A8: Medium | B8: 20 | C8: =COUNTIFS('Test Cases'!$F$2:$F$80,$A8,'Test Cases'!$N$2:$N$80,"Pass")
A9: Low | B9: 3 | C9: =COUNTIFS('Test Cases'!$F$2:$F$80,$A9,'Test Cases'!$N$2:$N$80,"Pass")
A11: Can it be automated?
A12: Yes | B12: 67
A13: Partly | B13: 10
A14: No | B14: 2
A16: By group
A17: A. Getting to the seat map | B17: 5 | C17: =COUNTIFS('Test Cases'!$C$2:$C$80,$A17,'Test Cases'!$N$2:$N$80,"Pass")
A18: B. How the map is drawn | B18: 7 | C18: =COUNTIFS('Test Cases'!$C$2:$C$80,$A18,'Test Cases'!$N$2:$N$80,"Pass")
A19: C. Seat colours and labels | B19: 5 | C19: =COUNTIFS('Test Cases'!$C$2:$C$80,$A19,'Test Cases'!$N$2:$N$80,"Pass")
A20: D. Choosing a seat | B20: 9 | C20: =COUNTIFS('Test Cases'!$C$2:$C$80,$A20,'Test Cases'!$N$2:$N$80,"Pass")
A21: E. More than one passenger or flight | B21: 4 | C21: =COUNTIFS('Test Cases'!$C$2:$C$80,$A21,'Test Cases'!$N$2:$N$80,"Pass")
A22: F. Prices | B22: 5 | C22: =COUNTIFS('Test Cases'!$C$2:$C$80,$A22,'Test Cases'!$N$2:$N$80,"Pass")
A23: G. Fare packages | B23: 4 | C23: =COUNTIFS('Test Cases'!$C$2:$C$80,$A23,'Test Cases'!$N$2:$N$80,"Pass")
A24: H. Women-only seats | B24: 6 | C24: =COUNTIFS('Test Cases'!$C$2:$C$80,$A24,'Test Cases'!$N$2:$N$80,"Pass")
A25: I. Keeping the choice | B25: 4 | C25: =COUNTIFS('Test Cases'!$C$2:$C$80,$A25,'Test Cases'!$N$2:$N$80,"Pass")
A26: J. Errors and clashes | B26: 3 | C26: =COUNTIFS('Test Cases'!$C$2:$C$80,$A26,'Test Cases'!$N$2:$N$80,"Pass")
A27: K. Small screens and screen readers | B27: 2 | C27: =COUNTIFS('Test Cases'!$C$2:$C$80,$A27,'Test Cases'!$N$2:$N$80,"Pass")
A28: L. Economy and Business | B28: 6 | C28: =COUNTIFS('Test Cases'!$C$2:$C$80,$A28,'Test Cases'!$N$2:$N$80,"Pass")
... A32: P. Emergency exit seats | B32: 6 | C32: =COUNTIFS('Test Cases'!$C$2:$C$80,$A32,'Test Cases'!$N$2:$N$80,"Pass")
A34: Passed so far | B34: =COUNTIF('Test Cases'!$N$2:$N$80,"Pass")
A35: Failed so far | B35: =COUNTIF('Test Cases'!$N$2:$N$80,"Fail")
